browser_sdk/general_app.py
browser_sdk/math_app.py
browser_sdk/upload_file_s3.sh
xclass_sdk/__init__.py
xclass_sdk/chat_bot_app.py
xclass_sdk/chat_bot_fb_app.py
xclass_sdk/general_app.py
xclass_sdk/math_app.py
xclass_sdk/profile.py
xclass_sdk/xclass_helpers.py
xclass_sdk/chat_bot_fb/facebookApiSupporter.py
xclass_sdk/chat_bot_fb/logic.py
xclass_sdk/chat_bot_fb/main.py
xclass_sdk/chat_bot_fb/requirements.txt
xclass_sdk/chat_bot_fb/vercel.json
xclass_sdk/chat_bot_fb/xClassService.py
xclass_sdk/views/chat_bot.mustache
xclass_sdk/views/general_app.mustache
xclass_sdk/views/math_app.mustache
xclass_sdk/views/profile.mustache
xclass_sdk-2.1.3.dist-info/LICENSE.txt
xclass_sdk-2.1.3.dist-info/METADATA
xclass_sdk-2.1.3.dist-info/WHEEL
xclass_sdk-2.1.3.dist-info/top_level.txt
xclass_sdk-2.1.3.dist-info/RECORD
