Metadata-Version: 2.1
Name: xclass_sdk
Version: 2.1.3
Summary: X-Class SDK
Author-email: Trung Nguyen <lantrungseo@gmail.com>
Project-URL: Homepage, https://github.com/lantrungseo/xclass-sdk
Project-URL: Bug Tracker, https://github.com/lantrungseo/xclass-sdk
Classifier: Programming Language :: Python :: 3
Classifier: License :: OSI Approved :: MIT License
Classifier: Operating System :: OS Independent
Requires-Python: >=3.7
License-File: LICENSE.txt
Requires-Dist: requests <3,>=2
Requires-Dist: pystache >=0.6.0
